sdypy/__init__.py
sdypy/view/__init__.py
sdypy/view/pyvista_3D.py
sdypy_view-0.1.1.dist-info/METADATA
sdypy_view-0.1.1.dist-info/WHEEL
sdypy_view-0.1.1.dist-info/RECORD
